klang_valley_transit/__init__.py
klang_valley_transit/graphAlgorithm.py
klang_valley_transit/trainNetwork.py
klang_valley_transit/trainNetwork.save.json
klang_valley_transit/data/bfs.json
klang_valley_transit/data/lrtAmpangCoordinates.json
klang_valley_transit/data/lrtKelanaJayaCoordinates.json
klang_valley_transit/data/lrtSriPetalingCoordinates.json
klang_valley_transit/data/mrtKajangCoordinates.json
klang_valley_transit/data/mrtPutrajayaCoordinates.json
klang_valley_transit/helper/__init__.py
klang_valley_transit/helper/dataStructure/__init__.py
klang_valley_transit/helper/dataStructure/graph.py
klang_valley_transit/helper/dataStructure/queue.py
klang_valley_transit/helper/dataStructure/stack.py
klang_valley_transit/helper/distance/__init__.py
klang_valley_transit/helper/distance/haversineDistance.py
klang_valley_transit/helper/model/__init__.py
klang_valley_transit/helper/model/baseModel.py
klang_valley_transit-1.0.2.data/scripts/test.py
klang_valley_transit-1.0.2.dist-info/METADATA
klang_valley_transit-1.0.2.dist-info/WHEEL
klang_valley_transit-1.0.2.dist-info/top_level.txt
klang_valley_transit-1.0.2.dist-info/RECORD
