Metadata-Version: 2.1
Name: klang-valley-transit
Version: 1.0.2
Summary: Graph, Graph Algorithm, and Klang Valley Transit Routing
Home-page: UNKNOWN
Author: Chin Yan
Author-email: cy.python.91@gmail.com
License: MIT
Platform: UNKNOWN
Requires-Dist: numpy
Requires-Dist: pydantic
